{"columns": ["symbol", "name", "exchange", "mic_code", "currency", "datetime", "timestamp", "last_quote_at", "open", "high", "low", "close", "volume", "previous_close", "change", "percent_change", "average_volume", "is_market_open", "fifty_two_week.low", "fifty_two_week.high", "fifty_two_week.low_change", "fifty_two_week.high_change", "fifty_two_week.low_change_percent", "fifty_two_week.high_change_percent", "fifty_two_week.range"], "title": "ALO:Euronext \u2014 Quote", "currency": "EUR", "exchange": "Euronext", "is_market_open": false, "organization": "Market Data", "source": {"organization": "Market Data", "organization_acronym": "Market Data"}, "results": [["ALO", "Alstom SA", "Euronext", "XPAR", "EUR", "2026-07-21", 1784648116, 1784648116, "15.90000", "16.08000", "15.75500", "15.96500", "1093334", "15.84500", "0.12000", "0.75734", "1606461", false, "14.72000", "30.23000", "1.24500", "-14.26500", "8.45788", "-47.18822", "14.72000 - 30.23000"]], "row_count": 1, "preview_row_count": 1, "sampled": false, "sampling_note": "Showing all rows.", "refresh_source": "Yahoo Finance chart endpoint (secondary live source)", "refreshed_at": "2026-07-21T17:55:46+00:00"}