{"columns": ["symbol", "name", "exchange", "mic_code", "currency", "datetime", "timestamp", "last_quote_at", "open", "high", "low", "close", "volume", "previous_close", "change", "percent_change", "average_volume", "is_market_open", "fifty_two_week.low", "fifty_two_week.high", "fifty_two_week.low_change", "fifty_two_week.high_change", "fifty_two_week.low_change_percent", "fifty_two_week.high_change_percent", "fifty_two_week.range"], "title": "DE \u2014 Quote", "currency": "USD", "exchange": "NYSE", "is_market_open": false, "organization": "Market Data", "source": {"organization": "Market Data", "organization_acronym": "Market Data"}, "results": [["DE", "Deere & Company", "NYSE", "XNYS", "USD", "2026-07-10", 1783713602, 1783713602, "596.21997", "599.44000", "586.67999", "586.86000", "782100", "592.90002", "-6.04002", "-1.01873", "1335000", false, "433.00000", "674.19000", "153.86000", "-87.33000", "35.53349", "-12.95332", "433.00000 - 674.19000"]], "row_count": 1, "preview_row_count": 1, "sampled": false, "sampling_note": "Showing all rows.", "refresh_source": "Yahoo Finance chart endpoint (secondary live source)", "refreshed_at": "2026-07-11T23:36:35+00:00"}