{"columns": ["symbol", "name", "exchange", "mic_code", "currency", "datetime", "timestamp", "last_quote_at", "open", "high", "low", "close", "volume", "previous_close", "change", "percent_change", "average_volume", "is_market_open", "fifty_two_week.low", "fifty_two_week.high", "fifty_two_week.low_change", "fifty_two_week.high_change", "fifty_two_week.low_change_percent", "fifty_two_week.high_change_percent", "fifty_two_week.range"], "title": "BDC \u2014 Quote", "currency": "USD", "exchange": "NYSE", "is_market_open": false, "organization": "Market Data", "source": {"organization": "Market Data", "organization_acronym": "Market Data"}, "results": [["BDC", "Belden Inc.", "NYSE", "XNYS", "USD", "2026-07-22", 1784742688, 1784742688, "100.73000", "104.50000", "101.04000", "103.93000", "228271", "102.05000", "1.88000", "1.84223", "627100", false, "98.00000", "159.99000", "5.93000", "-56.06000", "6.05102", "-35.03969", "98.00000 - 159.99000"]], "row_count": 1, "preview_row_count": 1, "sampled": false, "sampling_note": "Showing all rows.", "refresh_source": "Yahoo Finance chart endpoint (secondary live source)", "refreshed_at": "2026-07-22T17:51:39+00:00"}