{"columns": ["symbol", "name", "exchange", "mic_code", "currency", "datetime", "timestamp", "last_quote_at", "open", "high", "low", "close", "volume", "previous_close", "change", "percent_change", "average_volume", "is_market_open", "fifty_two_week.low", "fifty_two_week.high", "fifty_two_week.low_change", "fifty_two_week.high_change", "fifty_two_week.low_change_percent", "fifty_two_week.high_change_percent", "fifty_two_week.range"], "title": "ALO:Euronext \u2014 Quote", "currency": "EUR", "exchange": "Euronext", "is_market_open": false, "organization": "Market Data", "source": {"organization": "Market Data", "organization_acronym": "Market Data"}, "results": [["ALO", "Alstom SA", "Euronext", "XPAR", "EUR", "2026-07-23", 1784820952, 1784820952, "15.95000", "16.20000", "15.91000", "16.02500", "1426923", "16.12500", "-0.10000", "-0.62016", "1606461", false, "14.72000", "30.23000", "1.30500", "-14.20500", "8.86549", "-46.98975", "14.72000 - 30.23000"]], "row_count": 1, "preview_row_count": 1, "sampled": false, "sampling_note": "Showing all rows.", "refresh_source": "Yahoo Finance chart endpoint (secondary live source)", "refreshed_at": "2026-07-23T23:11:20+00:00"}